trouting/__init__.py
trouting/core.py
trouting/py.typed
trouting-0.3.3.dist-info/LICENSE
trouting-0.3.3.dist-info/METADATA
trouting-0.3.3.dist-info/WHEEL
trouting-0.3.3.dist-info/top_level.txt
trouting-0.3.3.dist-info/RECORD
