Metadata-Version: 2.1
Name: trouting
Version: 0.3.3
Summary: Trouting (short for Type Routing) is a simple class decorator that allows to define multiple interfaces for a method that behave differently depending on input types.
Author-email: Luca Soldaini <luca@soldaini.net>
License: Apache-2.0
Project-URL: Homepage, https://github.com/soldni/trouting
Project-URL: Source, https://github.com/soldni/trouting
Project-URL: Tracker, https://github.com/soldni/trouting/issues
Classifier: Development Status :: 5 - Production/Stable
Classifier: License :: OSI Approved :: Apache Software License
Classifier: Operating System :: OS Independent
Classifier: Programming Language :: Python :: 3
Classifier: Topic :: Software Development :: Libraries :: Python Modules
Classifier: Topic :: Utilities
Classifier: Typing :: Typed
Requires-Python: >=3.8
License-File: LICENSE
Requires-Dist: typing-extensions (>=4.3.0)
Provides-Extra: dev
Requires-Dist: black (>=22.6.0) ; extra == 'dev'
Requires-Dist: isort (>=5.10.1) ; extra == 'dev'
Requires-Dist: mypy (>=0.971) ; extra == 'dev'
Requires-Dist: pytest (>=5.2) ; extra == 'dev'
Requires-Dist: ipython (>=8.4.0) ; extra == 'dev'
Requires-Dist: autopep8 (>=1.7.0) ; extra == 'dev'
Requires-Dist: flake8 (>=5.0) ; extra == 'dev'
Requires-Dist: ipdb (>=0.13.0) ; extra == 'dev'
Requires-Dist: flake8-pyi (>=22.8.1) ; extra == 'dev'
Requires-Dist: Flake8-pyproject (>=1.1.0) ; extra == 'dev'
